candycrunch/__init__.py
candycrunch/analysis.py
candycrunch/candycrunch.pt
candycrunch/cli.py
candycrunch/glycans.pkl
candycrunch/glytoucan_mapping.pkl
candycrunch/model.py
candycrunch/prediction.py
candycrunch-0.6.0.dist-info/licenses/LICENSE
candycrunch-0.6.0.dist-info/METADATA
candycrunch-0.6.0.dist-info/WHEEL
candycrunch-0.6.0.dist-info/entry_points.txt
candycrunch-0.6.0.dist-info/top_level.txt
candycrunch-0.6.0.dist-info/RECORD
