Metadata-Version: 2.4
Name: candycrunch
Version: 0.6.0
Summary: Package for predicting glycan structure from LC-MS/MS data
Author-email: Daniel Bojar <daniel.bojar@gu.se>
License: MIT
Project-URL: Homepage, https://github.com/BojarLab/CandyCrunch
Classifier: Programming Language :: Python :: 3
Classifier: License :: OSI Approved :: MIT License
Classifier: Operating System :: OS Independent
Requires-Python: >=3.9
License-File: LICENSE
Requires-Dist: glycowork~=1.6.1
Requires-Dist: requests
Requires-Dist: regex
Requires-Dist: networkx
Requires-Dist: scipy
Requires-Dist: torch~=2.1
Requires-Dist: numpy_indexed
Requires-Dist: seaborn
Requires-Dist: pandas
Requires-Dist: statsmodels
Requires-Dist: pymzml
Requires-Dist: pyteomics
Requires-Dist: lxml
Requires-Dist: torchvision
Requires-Dist: openpyxl
Requires-Dist: tabulate
Requires-Dist: matplotlib
Requires-Dist: pytest
Dynamic: license-file
